rational_rc/__init__.py
rational_rc/carbonation.py
rational_rc/chloride.py
rational_rc/corrosion.py
rational_rc/cracking.py
rational_rc/math_helper.py
rational_rc/membrane.py
rational_rc-0.2.4.dist-info/LICENSE.txt
rational_rc-0.2.4.dist-info/METADATA
rational_rc-0.2.4.dist-info/WHEEL
rational_rc-0.2.4.dist-info/top_level.txt
rational_rc-0.2.4.dist-info/RECORD
