Metadata-Version: 2.1
Name: rational-rc
Version: 0.2.4
Summary: Rational RC is a practical life cycle deterioration modeling framework. It utilizes field survey data and provides probabilistic predictions of RC structure deterioration through different stages of the service life cycle. It covers various deterioration mechanisms such as membrane deterioration, concrete carbonation and chloride penetration, corrosion, and cracking.
Author-email: Gang Li <ganglix@gmail.com>
Project-URL: Homepage, https://github.com/ganglix/rational-rc
Project-URL: Documentation, https://rational-rc.readthedocs.io/en/latest/
Classifier: Development Status :: 4 - Beta
Classifier: Programming Language :: Python :: 3.9
Classifier: License :: OSI Approved :: GNU General Public License v3 (GPLv3)
Classifier: Operating System :: OS Independent
Requires-Python: >=3.9
License-File: LICENSE.txt
Requires-Dist: matplotlib >=3.7.2
Requires-Dist: numpy >=1.25.1
Requires-Dist: pandas >=2.0.3
Requires-Dist: scipy >=1.11.1
Provides-Extra: doc
Requires-Dist: ipython >=8.14.0 ; extra == 'doc'
Requires-Dist: sphinx ==6.2.1 ; extra == 'doc'
Requires-Dist: nbsphinx ==0.9.2 ; extra == 'doc'
Requires-Dist: nbsphinx-link ==1.3.0 ; extra == 'doc'
Requires-Dist: sphinx-rtd-theme ==1.2.2 ; extra == 'doc'
Requires-Dist: sphinx-math-dollar ==1.2.1 ; extra == 'doc'
Requires-Dist: recommonmark ==0.7.1 ; extra == 'doc'
Requires-Dist: toml >=0.10.2 ; extra == 'doc'
Provides-Extra: test
